01. Dataflow Modelling/fullsubstractor.v
module fullsubstractor (a,b,c,diff,borr);

    input a,b,c;
    output diff,borr;

    assign diff = a^b^c;
    assign borr = ~a&c | ~a&b | b&c;
    
endmodule

1. Dataflow Modelling/fullsubstractor_tb.v
module fullsubstractor_tb;

    reg a,b,c;
    wire diff,borr;

    fullsubstractor uut(a,b,c,diff,borr);

    initial 
    begin
        $monitor("a=%0b,b=%0b,c=%0b,diff=%0b,borr=%0b",a,b,c,diff,borr);
        a=0;b=0;c=0;
        #5
        a=0;b=0;c=1;
        #5
        a=0;b=1;c=0;
        #5
        a=0;b=1;c=1;
        #5
        a=1;b=0;c=0;
        #5
        a=1;b=0;c=1;
        #5
        a=1;b=1;c=0;
        #5
        a=1;b=1;c=1;
        #65  $finish;   
    end

    initial
    begin
        $dumpfile("fullsubstractor.vcd");
        $dumpvars;
    end

endmodule

01. Dataflow Modelling/fullsubstractor.vcd
$date
	Fri May 20 16:16:11 2022
$end
$version
	Icarus Verilog
$end
$timescale
	1s
$end
$scope module fullsubstractor_tb $end
$var wire 1 ! diff $end
$var wire 1 " borr $end
$var reg 1 # a $end
$var reg 1 $ b $end
$var reg 1 % c $end
$scope module uut $end
$var wire 1 # a $end
$var wire 1 $ b $end
$var wire 1 " borr $end
$var wire 1 % c $end
$var wire 1 ! diff $end
$upscope $end
$upscope $end
$enddefinitions $end
#0
$dumpvars
0%
0$
0#
0"
0!
$end
#5
1"
1!
1%
#10
0%
1$
#15
0!
1%
#20
0"
1!
0%
0$
1#
#25
0!
1%
#30
0%
1$
#35
1"
1!
1%
