01. Dataflow Modelling/fulladder.v
module full_adder(a,b,c,sum,cout);
  
  //direction of the ports
  input a,b,c;
  output sum,cout;
  
  //logic-data flow model
  assign sum=a^b^c;
  assign cout=a&b|b&c|c&a;
  
endmodule

01. Dataflow Modelling/fulladder_tb.v
module tb;
  
  //direction of ports
  reg a,b,c;
  wire sum,cout;
  
  //instantiation
  full_adder uut(a,b,c,sum,cout);//order mapping
  
  initial
    begin
      $monitor("a=%0b,b=%0b,c=%0b,sum=%0b,cout=%0b",a,b,c,sum,cout);
      
       a=0;b=0;c=0;
        #5
       a=0;b=0;c=1;
        #5
       a=0;b=1;c=0;
        #5
       a=0;b=1;c=1;
        #5
       a=1;b=0;c=0;
        #5
       a=1;b=0;c=1;
        #5
       a=1;b=1;c=0;
        #5
       a=1;b=1;c=1;
      
      #100 $finish;
    end
  
  initial
    begin
      $dumpfile("fulladder.vcd");
      $dumpvars;
      
    end
endmodule

01. Dataflow Modelling/fulladder.vcd
$date
	Fri May 20 15:22:23 2022
$end
$version
	Icarus Verilog
$end
$timescale
	1s
$end
$scope module tb $end
$var wire 1 ! sum $end
$var wire 1 " cout $end
$var reg 1 # a $end
$var reg 1 $ b $end
$var reg 1 % c $end
$scope module uut $end
$var wire 1 # a $end
$var wire 1 $ b $end
$var wire 1 % c $end
$var wire 1 " cout $end
$var wire 1 ! sum $end
$upscope $end
$upscope $end
$enddefinitions $end
#0
$dumpvars
0%
0$
0#
0"
0!
$end
#5
1!
1%
#10
0%
1$
#15
1"
0!
1%
#20
0"
1!
0%
0$
1#
#25
1"
0!
1%
#30
0%
1$
#35
1!
1%
