02. Behavioural Model/fullsubstractor.v
module fullsubs(a,b,c,diff,borr);

    input a,b,c;
    output reg diff,borr;

    always @(a,b,c) begin
        case ({a,b,c})
            3'b000:begin
                diff=0;borr=0;
            end
            3'b001:begin
                diff=1;borr=1;
            end
            3'b010:begin
                diff=1;borr=1;
            end
            3'b011:begin
                diff=0;borr=1;
            end     
            3'b100:begin
                diff=1;borr=0;
            end
            3'b101:begin
                diff=0;borr=0;
            end
            3'b110:begin
                diff=0;borr=0;
            end
            3'b111:begin
                diff=1;borr=1;
            end        
        endcase
    end

endmodule

2. Behavioural Model/fullsubstractor_tb.v
module tb ;

reg a,b,c;
wire diff,borr;

fullsubs uut (a,b,c,diff,borr);

initial begin
    $monitor("t=%0t     a=%0b,b=%0b,c=%0b,diff=%0b,borr=%0b",$time,a,b,c,diff,borr);
    a=0;b=0;c=0; #10
    a=0;b=0;c=1; #10
    a=0;b=1;c=0; #10
    a=0;b=1;c=1; #10
    a=1;b=0;c=0; #10
    a=1;b=0;c=1; #10
    a=1;b=1;c=0; #10
    a=1;b=1;c=1; #10
    $finish;
end

initial begin
    $dumpfile("fullsubs.vcd");
    $dumpvars;
end
    
endmodule

2. Behavioural Model/fullsubs.vcd
$date
	Mon May 23 20:27:20 2022
$end
$version
	Icarus Verilog
$end
$timescale
	1s
$end
$scope module tb $end
$var wire 1 ! diff $end
$var wire 1 " borr $end
$var reg 1 # a $end
$var reg 1 $ b $end
$var reg 1 % c $end
$scope module uut $end
$var wire 1 # a $end
$var wire 1 $ b $end
$var wire 1 % c $end
$var reg 1 " borr $end
$var reg 1 ! diff $end
$upscope $end
$upscope $end
$enddefinitions $end
#0
$dumpvars
0%
0$
0#
0"
0!
$end
#10
1"
1!
1%
#20
0%
1$
#30
0!
1%
#40
0"
1!
0%
0$
1#
#50
0!
1%
#60
0%
1$
#70
1"
1!
1%
