07. Parameterized Ripple Carry Adder/fulladder.v
module fulladder(a,b,c,sum,cout);

    input a,b,c;
    output sum,cout;
  	assign {cout,sum} = a+b+c;
    

endmodule

2. Behavioural Model/fulladder_tb.v
module tb ;

reg a,b,c;
wire sum,cout;

fulladder uut (a,b,c,sum,cout);

initial begin
    $monitor("t=%0t     a=%0b,b=%0b,c=%0b,sum=%0b,cout=%0b",$time,a,b,c,sum,cout);
    a=0;b=0;c=0; #10
    a=0;b=0;c=1; #10
    a=0;b=1;c=0; #10
    a=0;b=1;c=1; #10
    a=1;b=0;c=0; #10
    a=1;b=0;c=1; #10
    a=1;b=1;c=0; #10
    a=1;b=1;c=1; #10
    $finish;
end

initial begin
    $dumpfile("fulladder.vcd");
    $dumpvars;
end
    
endmodule

2. Behavioural Model/fulladder.vcd
$date
	Mon May 23 20:16:00 2022
$end
$version
	Icarus Verilog
$end
$timescale
	1s
$end
$scope module tb $end
$var wire 1 ! sum $end
$var wire 1 " cout $end
$var reg 1 # a $end
$var reg 1 $ b $end
$var reg 1 % c $end
$scope module uut $end
$var wire 1 # a $end
$var wire 1 $ b $end
$var wire 1 % c $end
$var reg 1 " cout $end
$var reg 1 ! sum $end
$upscope $end
$upscope $end
$enddefinitions $end
#0
$dumpvars
0%
0$
0#
0"
0!
$end
#10
1!
1%
#20
0%
1$
#30
1"
0!
1%
#40
0"
1!
0%
0$
1#
#50
1"
0!
1%
#60
0%
1$
#70
1!
1%
